{
	"name": "Visi's Theme",
	"author": "Vicent Baeza",
	"maintainers": [
		"Vicent Baeza <vicentbaeza7@gmail.com>"
	],
	"type": "dark",
	"colors": {
		"contrastActiveBorder": null,
		"contrastBorder": "#282B3C",
		"focusBorder": "#282B3C",
		"foreground": "#ffffff",
		"widget.shadow": "#232635",
		"selection.background": "#3C435E",
		"descriptionForeground": null,
		"errorForeground": "#EF5350",
		"button.background": "#7e57c2cc",
		"button.foreground": "#ffffffcc",
		"button.hoverBackground": "#7e57c2",
		"dropdown.background": "#292D3E",
		"dropdown.border": "#7e57c2",
		"dropdown.foreground": "#ffffffcc",
		"input.background": "#414863",
		"input.border": "#7e57c2",
		"input.foreground": "#ffffffcc",
		"input.placeholderForeground": "#ffffffcc",
		"inputOption.activeBorder": "#ffffffcc",
		"inputValidation.errorBackground": "#ef5350f2",
		"inputValidation.errorBorder": "#EF5350",
		"inputValidation.infoBackground": "#64b5f6f2",
		"inputValidation.infoBorder": "#64B5F6",
		"inputValidation.warningBackground": "#ffca28f2",
		"inputValidation.warningBorder": "#FFCA28",
		"scrollbar.shadow": "#292D3E00",
		"scrollbarSlider.activeBackground": "#694CA4cc",
		"scrollbarSlider.background": "#694CA466",
		"scrollbarSlider.hoverBackground": "#694CA4cc",
		"badge.background": "#7e57c2",
		"badge.foreground": "#ffffff",
		"list.activeSelectionBackground": "#7e57c2",
		"list.activeSelectionForeground": "#ffffff",
		"list.dropBackground": "#2E3245",
		"list.focusBackground": "#0000002e",
		"list.focusForeground": "#ffffff",
		"list.highlightForeground": "#ffffff",
		"list.hoverBackground": "#0000001a",
		"list.hoverForeground": "#ffffff",
		"list.inactiveSelectionBackground": "#929ac90d",
		"list.inactiveSelectionForeground": "#929ac9",
		"activityBar.background": "#282C3D",
		"activityBar.foreground": "#eeffff",
		"activityBar.border": "#282C3D",
		"activityBarBadge.background": "#7e57c2",
		"activityBarBadge.foreground": "#ffffff",
		"sideBar.background": "#292D3E",
		"sideBar.foreground": "#6C739A",
		"sideBar.border": "#282B3C",
		"sideBarTitle.foreground": "#eeffff",
		"sideBarSectionHeader.background": "#292D3E",
		"sideBarSectionHeader.foreground": "#eeffff",
		"editorGroup.border": "#2E3245",
		"editorGroup.dropBackground": "#7e57c273",
		"editorGroupHeader.noTabsBackground": "#32374C",
		"editorGroupHeader.tabsBackground": "#31364a",
		"editorGroupHeader.tabsBorder": "#262A39",
		"tab.activeBackground": "#292D3E",
		"tab.activeForeground": "#eeffff",
		"tab.border": "#272B3B",
		"tab.activeBorder": "#262A39",
		"tab.unfocusedActiveBorder": "#262A39",
		"tab.inactiveBackground": "#31364A",
		"tab.inactiveForeground": "#929ac9",
		"tab.unfocusedActiveForeground": null,
		"tab.unfocusedInactiveForeground": null,
		"editor.background": "#292D3E",
		"editor.foreground": "#BFC7D5",
		"editorLineNumber.foreground": "#4c5374",
		"editorLineNumber.activeForeground": "#eeffff",
		"editorCursor.foreground": "#7e57c2",
		"editorCursor.background": null,
		"editor.selectionBackground": "#7580B850",
		"editor.selectionHighlightBackground": "#383D51",
		"editor.inactiveSelectionBackground": "#7e57c25a",
		"editor.wordHighlightBackground": "#32374D",
		"editor.wordHighlightStrongBackground": "#2E3250",
		"editor.findMatchBackground": "#7e57c25a",
		"editor.findMatchHighlightBackground": "#2E3248",
		"editor.findRangeHighlightBackground": null,
		"editor.hoverHighlightBackground": "#7e57c25a",
		"editor.lineHighlightBackground": "#0003",
		"editor.lineHighlightBorder": null,
		"editorLink.activeForeground": null,
		"editor.rangeHighlightBackground": "#7e57c25a",
		"editorWhitespace.foreground": null,
		"editorIndentGuide.background": "#4E557980",
		"editorRuler.foreground": null,
		"editorCodeLens.foreground": "#FFCA28",
		"editorBracketMatch.background": null,
		"editorBracketMatch.border": null,
		"editorOverviewRuler.currentContentForeground": "#7e57c2",
		"editorOverviewRuler.incomingContentForeground": "#7e57c2",
		"editorOverviewRuler.commonContentForeground": "#7e57c2",
		"editorError.foreground": "#EF5350",
		"editorError.border": null,
		"editorWarning.foreground": "#FFCA28",
		"editorWarning.border": null,
		"editorGutter.background": null,
		"editorGutter.modifiedBackground": "#e2b93d",
		"editorGutter.addedBackground": "#9CCC65",
		"editorGutter.deletedBackground": "#EF5350",
		"diffEditor.insertedTextBackground": "#99b76d23",
		"diffEditor.removedTextBackground": "#ef535033",
		"editorWidget.background": "#31364a",
		"editorWidget.border": null,
		"editorSuggestWidget.background": "#2C3043",
		"editorSuggestWidget.border": "#2B2F40",
		"editorSuggestWidget.foreground": "#bfc7d5",
		"editorSuggestWidget.highlightForeground": "#ffffff",
		"editorSuggestWidget.selectedBackground": "#7e57c2",
		"editorHoverWidget.background": "#292D3E",
		"editorHoverWidget.border": "#7e57c2",
		"debugExceptionWidget.background": "#292D3E",
		"debugExceptionWidget.border": "#7e57c2",
		"editorMarkerNavigation.background": "#31364a",
		"editorMarkerNavigationError.background": "#EF5350",
		"editorMarkerNavigationWarning.background": "#FFCA28",
		"peekView.border": "#7e57c2",
		"peekViewEditor.background": "#232635",
		"peekViewEditor.matchHighlightBackground": "#7e57c25a",
		"peekViewResult.background": "#2E3245",
		"peekViewResult.fileForeground": "#eeffff",
		"peekViewResult.lineForeground": "#eeffff",
		"peekViewResult.matchHighlightBackground": "#7e57c25a",
		"peekViewResult.selectionBackground": "#2E3250",
		"peekViewResult.selectionForeground": "#eeffff",
		"peekViewTitle.background": "#292D3E",
		"peekViewTitleDescription.foreground": "#697098",
		"peekViewTitleLabel.foreground": "#eeffff",
		"merge.currentHeaderBackground": "#7e57c25a",
		"merge.currentContentBackground": null,
		"merge.incomingHeaderBackground": "#7e57c25a",
		"merge.incomingContentBackground": null,
		"merge.border": null,
		"panel.background": "#292D3E",
		"panel.border": "#282B3C",
		"panelTitle.activeBorder": "#7e57c2",
		"panelTitle.activeForeground": "#eeffff",
		"panelTitle.inactiveForeground": "#bfc7d580",
		"statusBar.background": "#282C3D",
		"statusBar.foreground": "#676E95",
		"statusBar.border": "#262A39",
		"statusBar.debuggingBackground": "#202431",
		"statusBar.debuggingForeground": null,
		"statusBar.debuggingBorder": "#1F2330",
		"statusBar.noFolderForeground": null,
		"statusBar.noFolderBackground": "#292D3E",
		"statusBar.noFolderBorder": "#25293A",
		"statusBarItem.activeBackground": "#202431",
		"statusBarItem.hoverBackground": "#202431",
		"statusBarItem.prominentBackground": "#202431",
		"statusBarItem.prominentHoverBackground": "#202431",
		"titleBar.activeBackground": "#292d3e",
		"titleBar.activeForeground": "#eeefff",
		"titleBar.border": "#30364c",
		"titleBar.inactiveBackground": "#30364c",
		"titleBar.inactiveForeground": null,
		"notifications.background": "#292D3E",
		"notifications.foreground": "#ffffffcc",
		"notificationLink.foreground": "#80CBC4",
		"extensionButton.prominentForeground": "#ffffffcc",
		"extensionButton.prominentBackground": "#7e57c2cc",
		"extensionButton.prominentHoverBackground": "#7e57c2",
		"pickerGroup.foreground": "#d1aaff",
		"pickerGroup.border": "#2E3245",
		"terminal.ansiWhite": "#ffffff",
		"terminal.ansiBlack": "#676E95",
		"terminal.ansiBlue": "#82AAFF",
		"terminal.ansiCyan": "#89DDFF",
		"terminal.ansiGreen": "#a9c77d",
		"terminal.ansiMagenta": "#C792EA",
		"terminal.ansiRed": "#ff5572",
		"terminal.ansiYellow": "#FFCB6B",
		"terminal.ansiBrightWhite": "#ffffff",
		"terminal.ansiBrightBlack": "#676E95",
		"terminal.ansiBrightBlue": "#82AAFF",
		"terminal.ansiBrightCyan": "#89DDFF",
		"terminal.ansiBrightGreen": "#C3E88D",
		"terminal.ansiBrightMagenta": "#C792EA",
		"terminal.ansiBrightRed": "#ff5572",
		"terminal.ansiBrightYellow": "#FFCB6B",
		"debugToolBar.background": "#292D3E",
		"welcomePage.buttonBackground": null,
		"welcomePage.buttonHoverBackground": null,
		"walkThrough.embeddedEditorBackground": "#232635",
		"gitDecoration.modifiedResourceForeground": "#e2c08de6",
		"gitDecoration.deletedResourceForeground": "#EF535090",
		"gitDecoration.untrackedResourceForeground": "#a9c77dff",
		"gitDecoration.ignoredResourceForeground": "#69709890",
		"gitDecoration.conflictingResourceForeground": "#FFEB95CC",
		"breadcrumb.foreground": "#6c739a",
		"breadcrumb.focusForeground": "#bfc7d5",
		"breadcrumb.activeSelectionForeground": "#eeffff",
		"breadcrumbPicker.background": "#292D3E"
	},
	"tokenColors": [
		{
			"name": "Global settings",
			"scope": [
                "",
                "variable.other",
				"string.unquoted.argument",
				"string.interpolated.backtick.shell",	
                "entity.name.type.template",
			],
			"settings": {
				"foreground": "#eeffff"
			}
		},
		{
			"name": "Punctuation",
			"scope": [
				"punctuation",
                "meta.tag.inline.any",
                "punctuation.definition.variable.shell variable.other.normal.shell",
                "keyword.control.clause.bodyend",
                "punctuation.definition.constant.math.tex",
                "meta.brace",
                "meta.preprocessor.string",
                "string.unquoted.preprocessor",
                "meta.parens",
                "punctuation.separator.colon.access.control",
			],
			"settings": {
				"foreground": "#bfc7d5"
			}
		},
		{
			"name": "Comment",
			"scope": [
				"comment",
				"punctuation.definition.tag.cs",
				"punctuation.definition.comment"
			],
			"settings": {
				"foreground": "#8189b8",
				"fontStyle": "italic"
			}
		},
		{
			"name": "Comment Highlights",
			"scope": [
				"entity.name.tag.localname.cs",
				"meta.tag.cs",
			],
			"settings":{
				"foreground": "#c5ccda",
				"fontStyle": "italic"
			}
		},
		{
			"name": "String",
			"scope": [
				"string",
				"punctuation.definition.string",
                "constant.other.atom.quoted.prolog",
                "support.class.math.block.tex",
                "support.class.math.block.environment.latex",
			],
			"settings": {
				"foreground": "#C3E88D",		
			}
		},
		{
			"name": "RegExp String / Escaped chars",
			"scope": [
				"string.regexp",
				"string.regexp keyword.other",
				"string.regexp",
				"constant.character.escape",
				"punctuation.definition.regexp",
                "string.quoted.double constant.character.escape.cs",
                "constant.other.atom.quoted",
			],
			"settings": {
				"foreground": "#80CBC4"
			}
		},
		{
			"name": "String Unquoted",
			"scope": "string.unquoted",
			"settings": {
				"foreground": "#bfc7d5"
			}
		},
		{
			"name": "Constants, Tags, Wildcards & Preprocessor definitions",
			"scope": [
				"constant.numeric",
				"constant.character.numeric",
				"constant.language.boolean",
				"constant.language.null",
				"constant.language",
				"punctuation.definition.constant",
				"comment.wildcard",
				"entity.name.function.preprocessor",
				"invalid.illegal.constant",
				"support.constant.subsections",
				"entity.name.function.label.ahk",
				"constant.keyword",
                "support.constant.property-value",
                "keyword.other.unit",
                "constant.other.color",
                "punctuation.separator.decimal.period",
                "constant.character.entity",
                "constant.character.math.tex"
			],
			"settings": {
				"foreground": "#ffae6b"
			}
		},
		{
			"name": "Operators",
			"scope": [
				"keyword.operator",
				"keyword.operator.bitwise.shift",
				"punctuation.separator.continuation",
				"punctuation.definition.tag",
				"entity.name.function.operator",
				
				"keyword.operator.assignment.arithmetic",
				"keyword.operator.assignment.compound",
				"punctuation.separator.question-mark",
				"punctuation.accessor",
				
				"punctuation.definition.equals.colon",
				"punctuation.separator.period",
				"punctuation.separator.colon",
				"storage.modifier.reference",
				"storage.modifier.pointer",
				"punctuation.separator.dot-access",
				"punctuation.section.angle-brackets.begin.template.call.cpp",
				"punctuation.section.angle-brackets.end.template.call.cpp",
                "entity.name.tag.reference",
                "punctuation.definition.entity",
                "entity.name.tag.wildcard",
                "punctuation.separator.method",
                "punctuation.definition.constant.elixir",
                "keyword.symbol",
                "punctuation.separator.statement.and",
                "keyword.control.clause.bodybegin",
                "punctuation.definition.variable.elixir",
                "punctuation.math.operator.latex",
                "entity.name.function.member.overload",
                "keyword.control.if.prolog",
                "keyword.control.else.prolog",
                "keyword.control.cut.prolog",
            ],
			"settings": {
				"foreground": "#ff5572"
			}
		},
		{
			"name": "Functions",
			"scope": [
				"entity.name.function",
				"entity.name.type.module",
				"support.function",
				"support.module",
				"constant.other.symbol.prolog",
				"entity.name.tag",
				"meta.tag",
				"meta.function-call",
				"entity.name.function.clojure",
                "entity.other.attribute-name",
            ],
			"settings": {
				"foreground": "#fad87c"
			}
		},
		{
			"name": "Namespaces, Labels & ",
			"scope": [				
				"entity.name.namespace",
				"storage.namespace",
				"entity.name.namespace",
				"entity.name.type.namespace",
				"keyword.label",
				"entity.name.label",
				"variable.language.this",
				"keyword.other.this",
				"storage.modifier.import.java",
				"variable.parameter.function.language.special.self",
                "keyword.control.at-rule",
                "variable.language.java",
                "keyword.other.base",
                "meta.preprocessor",
                "keyword.control.directive",
                "keyword.control.directives",
                "entity.name.function.preprocessor",
            ],
			"settings": {
				"foreground": "#82AAFF"
			}
		},
		{
			"name": "Types, Tags, Prolog Variables & AHK Lang Constants",
			"scope": [
                
				"storage.type",
				"storage.namespace",
				"entity.name.type",
				"keyword.type",
				"keyword.other.var",
				"support.class",
				"variable.other.prolog",
				"entity.name.command",
				"constant.language.ahk",
				"entity.global.clojure",
				"entity.name.class",
				"entity.name.tag",
                "entity.other.attribute-name.class",
                "entity.other.attribute-name.pseudo-class",
                "entity.other.attribute-name.pseudo-element",
                "entity.other.attribute-name.attribute",
                "support.type.property-name",
                "punctuation.support.type.property-name.begin.json",
				"punctuation.support.type.property-name.end.json",
                "support.type.vendored.property-name",
                "variable.other.constant.elixir",
                "keyword.type",
                "variable.language.anonymous.prolog",
                "variable.parameter.uppercase.prolog",
                "variable.parameter.function.latex",
                "storage.type.template.argument",
            ],
			"settings": {
				"foreground": "#82e6ff"
			}
		},
		{
			"name": "Keywords, Storage modifiers",
			"scope": [
				"keyword.other",
				"keyword.control",
				"meta.head.struct",
				"storage.type.namespace.directive",
				"storage.modifier",
				"keyword.operator.new",
				"storage.type.class",
				"storage.type.function",
				"storage.type.struct",
				"storage.type.namespace",
				"storage.type.interface",
				"storage.type.enum",
				"storage.control",
                "entity.name.tag.css",
                "constant.other.symbol.elixir",
                "keyword.fsharp",
                "keyword.function",
                "keyword.interface",
                "keyword.map",
                "keyword.struct",
                "keyword.channel",
                "keyword.const",
                "keyword.package",
                "keyword.import",
                "keyword.operator.wordlike",
                "keyword.operator.sizeof",
                "keyword.operator.delete",
                "keyword.operator.alignof",
                "keyword.operator.typeid",
                "keyword.operator.cast",
                "keyword.operator.noexcept",
                "storage.type.template",
                "storage.type.template.argument.class",
                "storage.type.template.argument.struct",
                "storage.type.template.argument.typename",
            ],
			"settings": {
				"foreground": "#C792EA",
			}
		},
	],
}